jquery_querybuilder_psycopg2/__init__.py
jquery_querybuilder_psycopg2/py.typed
jquery_querybuilder_psycopg2-1.4.1.dist-info/LICENSE
jquery_querybuilder_psycopg2-1.4.1.dist-info/METADATA
jquery_querybuilder_psycopg2-1.4.1.dist-info/WHEEL
jquery_querybuilder_psycopg2-1.4.1.dist-info/top_level.txt
jquery_querybuilder_psycopg2-1.4.1.dist-info/RECORD
