Metadata-Version: 2.1
Name: jquery-querybuilder-psycopg2
Version: 1.4.1
Summary: Parse a jQuery QueryBuilder style rule set into a psycopg2.sql.Composable
Home-page: https://bitbucket.org/gclinch/jquery-querybuilder-psycopg2
Author: Graham Clinch
Author-email: g.clinch@lancaster.ac.uk
License: Apache License, Version 2.0
Platform: UNKNOWN
Classifier: Development Status :: 5 - Production/Stable
Classifier: License :: OSI Approved :: Apache Software License
Classifier: Topic :: Database
Requires-Dist: psycopg2
